{
    "version": 1,
    "notes": "",
    "documentation": "\"This file is a QMK Configurator export. You can import this at <https://config.qmk.fm>. It can also be used directly with QMK's source code.\n\nTo setup your QMK environment check out the tutorial: <https://docs.qmk.fm/#/newbs>\n\nYou can convert this file to a keymap.c using this command: `qmk json2c {keymap}`\n\nYou can compile this keymap using this command: `qmk compile {keymap}`\"\n",
    "keyboard": "xd75",
    "keymap": "jenspfeifle",
    "layout": "LAYOUT_ortho_5x15",
    "layers": [
        [
            "KC_GRV",
            "KC_1",
            "KC_2",
            "KC_3",
            "KC_4",
            "KC_5",
            "KC_NO",
            "KC_DEL",
            "KC_NO",
            "KC_6",
            "KC_7",
            "KC_8",
            "KC_9",
            "KC_0",
            "KC_NO",
            "KC_ESC",
            "KC_Q",
            "KC_W",
            "KC_E",
            "KC_R",
            "KC_T",
            "KC_NO",
            "KC_PGUP",
            "KC_NO",
            "KC_Y",
            "KC_U",
            "KC_I",
            "KC_O",
            "KC_P",
            "KC_QUOT",
            "LCTL_T(KC_LCBR)",
            "KC_A",
            "KC_S",
            "KC_D",
            "KC_F",
            "KC_G",
            "KC_NO",
            "KC_PGDN",
            "KC_NO",
            "KC_H",
            "KC_J",
            "KC_K",
            "KC_L",
            "KC_SCLN",
            "RCTL_T(KC_RCBR)",
            "KC_LSPO",
            "KC_Z",
            "KC_X",
            "KC_C",
            "KC_V",
            "KC_B",
            "KC_NO",
            "KC_NO",
            "KC_NO",
            "KC_N",
            "KC_M",
            "KC_COMM",
            "KC_DOT",
            "KC_SLSH",
            "KC_RSPC",
            "KC_LCTL",
            "MO(3)",
            "KC_LGUI",
            "KC_LALT",
            "MO(2)",
            "KC_ENT",
            "KC_LGUI",
            "KC_NO",
            "MO(1)",
            "KC_SPC",
            "KC_BSPC",
            "KC_F5",
            "KC_F10",
            "KC_F11",
            "LSFT(KC_F11)"
        ],
        [
            "KC_NO",
            "KC_NO",
            "KC_NO",
            "KC_NO",
            "KC_NO",
            "KC_NO",
            "KC_NO",
            "KC_NO",
            "KC_NO",
            "KC_NO",
            "KC_NO",
            "KC_NO",
            "KC_NO",
            "KC_NO",
            "KC_NO",
            "KC_NO",
            "SGUI(KC_Q)",
            "KC_NO",
            "KC_NO",
            "KC_NO",
            "KC_NO",
            "KC_NO",
            "KC_NO",
            "LGUI(KC_BSPC)",
            "LGUI(KC_1)",
            "LGUI(KC_2)",
            "LGUI(KC_3)",
            "LGUI(KC_4)",
            "LGUI(KC_5)",
            "KC_NO",
            "KC_NO",
            "KC_NO",
            "KC_NO",
            "KC_NO",
            "KC_NO",
            "KC_NO",
            "KC_NO",
            "KC_NO",
            "KC_NO",
            "LGUI(KC_LEFT)",
            "LGUI(KC_DOWN)",
            "LGUI(KC_UP)",
            "LGUI(KC_RGHT)",
            "KC_NO",
            "KC_NO",
            "KC_LSFT",
            "KC_NO",
            "KC_NO",
            "KC_NO",
            "KC_NO",
            "KC_NO",
            "KC_NO",
            "KC_NO",
            "KC_NO",
            "LGUI(KC_6)",
            "LGUI(KC_7)",
            "LGUI(KC_8)",
            "LGUI(KC_9)",
            "LGUI(KC_0)",
            "KC_RSFT",
            "KC_LCTL",
            "KC_TRNS",
            "KC_NO",
            "KC_NO",
            "KC_TRNS",
            "KC_NO",
            "KC_NO",
            "KC_NO",
            "KC_TRNS",
            "KC_NO",
            "KC_NO",
            "KC_NO",
            "KC_NO",
            "KC_NO",
            "KC_NO"
        ],
        [
            "KC_ESC",
            "KC_F1",
            "KC_F2",
            "KC_F3",
            "KC_F4",
            "KC_F5",
            "KC_P7",
            "KC_P8",
            "KC_P9",
            "KC_F6",
            "KC_F7",
            "KC_F8",
            "KC_F9",
            "KC_F10",
            "KC_NO",
            "KC_TAB",
            "KC_NO",
            "KC_NO",
            "KC_NO",
            "KC_NO",
            "KC_PPLS",
            "KC_P4",
            "KC_P5",
            "KC_P6",
            "LSFT(KC_PGUP)",
            "KC_PGDN",
            "KC_PGUP",
            "LSFT(KC_PGDN)",
            "KC_NO",
            "KC_NO",
            "KC_NO",
            "KC_HOME",
            "LCTL(KC_LEFT)",
            "LCTL(KC_RGHT)",
            "KC_END",
            "KC_PAST",
            "KC_P1",
            "KC_P2",
            "KC_P3",
            "KC_LEFT",
            "KC_DOWN",
            "KC_UP",
            "KC_RGHT",
            "KC_NO",
            "KC_NO",
            "KC_NO",
            "KC_NO",
            "KC_NO",
            "KC_NO",
            "KC_NO",
            "KC_PSLS",
            "KC_P0",
            "KC_PDOT",
            "KC_PENT",
            "KC_MINS",
            "LSFT(KC_MINS)",
            "KC_EQL",
            "LSFT(KC_EQL)",
            "KC_NO",
            "KC_NO",
            "KC_NO",
            "KC_TRNS",
            "KC_NO",
            "KC_NO",
            "KC_TRNS",
            "KC_NO",
            "KC_NO",
            "KC_NO",
            "KC_TRNS",
            "KC_NO",
            "KC_NO",
            "KC_NO",
            "KC_NO",
            "KC_NO",
            "KC_NO"
        ],
        [
            "KC_NO",
            "EEP_RST",
            "KC_NO",
            "KC_NO",
            "KC_NO",
            "KC_NO",
            "RGB_SPI",
            "RGB_TOG",
            "RGB_SPD",
            "KC_NO",
            "KC_NO",
            "KC_NO",
            "KC_NO",
            "KC_NO",
            "KC_NO",
            "RESET",
            "KC_NO",
            "KC_NO",
            "KC_NO",
            "KC_NO",
            "KC_NO",
            "RGB_VAI",
            "RGB_MOD",
            "RGB_VAD",
            "KC_NO",
            "KC_NO",
            "KC_NO",
            "KC_NO",
            "KC_NO",
            "KC_NO",
            "KC_NO",
            "KC_NO",
            "KC_NO",
            "KC_NO",
            "KC_NO",
            "KC_NO",
            "RGB_HUI",
            "RGB_RMOD",
            "RGB_HUD",
            "KC_NO",
            "KC_NO",
            "KC_NO",
            "KC_NO",
            "KC_NO",
            "KC_NO",
            "KC_NO",
            "KC_NO",
            "KC_NO",
            "KC_NO",
            "KC_NO",
            "KC_NO",
            "RGB_SAI",
            "KC_NO",
            "RGB_SAD",
            "KC_NO",
            "KC_NO",
            "KC_NO",
            "KC_NO",
            "KC_NO",
            "KC_NO",
            "KC_NO",
            "KC_TRNS",
            "KC_NO",
            "KC_NO",
            "KC_TRNS",
            "KC_NO",
            "KC_NO",
            "KC_NO",
            "KC_TRNS",
            "KC_NO",
            "KC_NO",
            "KC_NO",
            "KC_NO",
            "KC_NO",
            "KC_NO"
        ]
    ],
    "author": ""
}